eoq3pyecoreutils/__init__.py
eoq3pyecoreutils/crudforpyecore.py
eoq3pyecoreutils/ecorecmdstream.py
eoq3pyecoreutils/ecoreconversionoptions.py
eoq3pyecoreutils/ecorefiletoeoqfile.py
eoq3pyecoreutils/ecoreutils.py
eoq3pyecoreutils/eoqfiletoecorefile.py
eoq3pyecoreutils/genericstopyecore.py
eoq3pyecoreutils/loadecorefile.py
eoq3pyecoreutils/pyecorepatch.py
eoq3pyecoreutils/pyecoretoeoq.py
eoq3pyecoreutils/saveecorefile.py
eoq3pyecoreutils/valuetopyecore.py
eoq3pyecoreutils-3.1.0.dist-info/licenses/LICENSE
eoq3pyecoreutils-3.1.0.dist-info/METADATA
eoq3pyecoreutils-3.1.0.dist-info/WHEEL
eoq3pyecoreutils-3.1.0.dist-info/top_level.txt
eoq3pyecoreutils-3.1.0.dist-info/RECORD
