Metadata-Version: 2.4
Name: eoq3pyecoreutils
Version: 3.1.0
Summary: A collection of pyecore to EOQ3 bridging tools.
Author-email: Bjoern Annighoefer <bjoern.annighoefer@ils.uni-stuttgart.de>
Project-URL: Homepage, https://gitlab.com/eoq/py/eoq3pyecoreutils
Project-URL: Issues, https://gitlab.com/eoq/py/eoq3pyecoreutils/-/issues
Classifier: Programming Language :: Python :: 3
Classifier: License :: OSI Approved :: MIT License
Classifier: Operating System :: OS Independent
Requires-Python: >=3.10
License-File: LICENSE
Requires-Dist: eoq3
Requires-Dist: pyecore
Dynamic: license-file
